pdf_manuscript/__init__.py
pdf_manuscript/dto/__init__.py
pdf_manuscript/helper/__init__.py
pdf_manuscript-0.0.1.dist-info/METADATA
pdf_manuscript-0.0.1.dist-info/WHEEL
pdf_manuscript-0.0.1.dist-info/top_level.txt
pdf_manuscript-0.0.1.dist-info/RECORD
