Metadata-Version: 2.1
Name: pdf-manuscript
Version: 0.0.1
Summary: Package to create PDF and Text files from TIFF images
Home-page: UNKNOWN
Author: Rui Meira
Author-email: ruimiguelcm96@gmail.com
License: UNKNOWN
Platform: UNKNOWN
Classifier: Programming Language :: Python :: 3
Classifier: License :: OSI Approved :: MIT License
Classifier: Operating System :: OS Independent
Requires-Python: >=3.6
